{"frameRate":24,"name":"Cat","version":"5.5","compatibleVersion":"5.5","armature":[{"type":"Armature","frameRate":24,"name":"Cat","aabb":{"x":-500.87,"y":-518.25,"width":1000,"height":1000},"bone":[{"name":"root"},{"length":24,"name":"貓","parent":"root","transform":{"x":-0.175,"y":-11,"skX":-89.5895,"skY":-89.5895}}],"slot":[{"name":"貓","parent":"貓"}],"skin":[{"slot":[{"name":"貓","display":[{"name":"貓","transform":{"x":7.24,"y":-0.75,"skX":89.59,"skY":89.59,"scX":0.05,"scY":0.05}}]}]}],"animation":[{"duration":20,"playTimes":0,"name":"Idle","bone":[{"name":"貓","translateFrame":[{"duration":10,"tweenEasing":0},{"duration":10,"tweenEasing":0,"y":-3},{"duration":0}]}]},{"duration":40,"playTimes":0,"name":"Run","bone":[{"name":"貓","rotateFrame":[{"duration":10,"tweenEasing":0},{"duration":20,"tweenEasing":0,"rotate":-10.41},{"duration":10,"tweenEasing":0,"rotate":9.59},{"duration":0,"rotate":-0.41}]}]}],"defaultActions":[{"gotoAndPlay":"Idle"}]},{"type":"Armature","frameRate":24,"name":"Char1","aabb":{"x":-449.3,"y":-468.95,"width":900,"height":925.5},"bone":[{"name":"root"},{"length":37.5,"name":"oc001_02_納哈特·維斯","parent":"root","transform":{"x":4.725,"y":12.05,"skX":-83.8858,"skY":-83.8858}}],"slot":[{"name":"oc001_02_納哈特·維斯","parent":"oc001_02_納哈特·維斯"}],"skin":[{"slot":[{"name":"oc001_02_納哈特·維斯","display":[{"name":"oc001_02_納哈特·維斯","transform":{"x":17.72,"y":-5.95,"skX":83.89,"skY":83.89,"scX":0.054,"scY":0.054}}]}]}],"animation":[{"duration":20,"playTimes":0,"name":"Idle","bone":[{"name":"oc001_02_納哈特·維斯","scaleFrame":[{"duration":10,"tweenEasing":0},{"duration":10,"tweenEasing":0,"x":1.05,"y":1.05},{"duration":0}]}]}],"defaultActions":[{"gotoAndPlay":"Idle"}]},{"type":"Armature","frameRate":24,"name":"Char2","aabb":{"x":-436.19,"y":-599.41,"width":900,"height":1199},"bone":[{"name":"root"},{"length":38,"name":"oc002_02_庫洛艾·巴尼特","parent":"root","transform":{"x":16.6,"y":21.675,"skX":-89.4761,"skY":-89.4761}}],"slot":[{"name":"oc002_02_庫洛艾·巴尼特","parent":"oc002_02_庫洛艾·巴尼特"}],"skin":[{"slot":[{"name":"oc002_02_庫洛艾·巴尼特","display":[{"name":"oc002_02_庫洛艾·巴尼特","transform":{"x":21.55,"y":-2.99,"skX":89.48,"skY":89.48,"scX":0.0417,"scY":0.0417}}]}]}],"animation":[{"duration":20,"playTimes":0,"name":"Idle","bone":[{"name":"oc002_02_庫洛艾·巴尼特","scaleFrame":[{"duration":10,"tweenEasing":0},{"duration":10,"tweenEasing":0,"x":1.05,"y":1.05},{"duration":0}]}]}],"defaultActions":[{"gotoAndPlay":"Idle"}]},{"type":"Armature","frameRate":24,"name":"Char3","aabb":{"x":-941.95,"y":-1078.92,"width":1900,"height":2150},"bone":[{"name":"root"},{"length":25,"name":"sc007_01_緹妲·拉賽爾","parent":"root","transform":{"x":13.475,"y":5.25,"skX":-109.4589,"skY":-109.4589}}],"slot":[{"name":"sc007_01_緹妲·拉賽爾","parent":"sc007_01_緹妲·拉賽爾"}],"skin":[{"slot":[{"name":"sc007_01_緹妲·拉賽爾","display":[{"name":"sc007_01_緹妲·拉賽爾","transform":{"x":10.46,"y":-2.06,"skX":109.46,"skY":109.46,"scX":0.0233,"scY":0.0233}}]}]}],"animation":[{"duration":20,"playTimes":0,"name":"Idle","bone":[{"name":"sc007_01_緹妲·拉賽爾","scaleFrame":[{"duration":10,"tweenEasing":0},{"duration":10,"tweenEasing":0,"x":1.05,"y":1.05},{"duration":0}]}]}],"defaultActions":[{"gotoAndPlay":"Idle"}]}]}